ipathelper/__init__.py
ipathelper/ipathelper.py
ipathelper-1.0.5.dist-info/LICENSE
ipathelper-1.0.5.dist-info/METADATA
ipathelper-1.0.5.dist-info/WHEEL
ipathelper-1.0.5.dist-info/top_level.txt
ipathelper-1.0.5.dist-info/RECORD
