Metadata-Version: 2.2
Name: ipathelper
Version: 1.0.5
Summary: PythonでIPATに投票する際に利用可能なモジュール
Author: Mikimini9627
Project-URL: Homepage, https://github.com/Mikimini9627/ipathelper
Project-URL: Repository, https://github.com/Mikimini9627/ipathelper
Classifier: Intended Audience :: Developers
Classifier: License :: OSI Approved :: MIT License
Classifier: Programming Language :: Python :: 3.12
Requires-Python: >=3.12
License-File: LICENSE
